LICENSE
README.md
py_mybatis.py
setup.py
mybatis_config/UserMapper.xml
mybatis_config/mybatis-3-config.dtd
mybatis_config/mybatis-3-mapper.dtd
mybatis_config/mybatis-config.xml
mybatis_config/spy.properties
py_mybatis.egg-info/PKG-INFO
py_mybatis.egg-info/SOURCES.txt
py_mybatis.egg-info/dependency_links.txt
py_mybatis.egg-info/requires.txt
py_mybatis.egg-info/top_level.txt
py_mybatis.egg-info/zip-safe
py_mybatis_java_lib/fastjson2-2.0.41.jar
py_mybatis_java_lib/jsqlparser-4.5.jar
py_mybatis_java_lib/mybatis-3.5.10.jar
py_mybatis_java_lib/mysql-connector-java-8.0.29.jar
py_mybatis_java_lib/p6spy-3.9.1.jar
py_mybatis_java_lib/pagehelper-5.3.2.jar
py_mybatis_java_lib/postgresql-42.6.0.jar
py_mybatis_java_lib/py_mybatis_java_module-0.0.1-SNAPSHOT.jar